create_agent/__init__.py
create_agent/cli.py
create_agent/utils.py
create_agent/templates/default/.env.example
create_agent/templates/default/.gitignore
create_agent/templates/default/README.md
create_agent/templates/default/requirements.txt
create_agent/templates/default/app/config.py
create_agent/templates/default/app/main.py
create_agent/templates/default/app/api/dependencies.py
create_agent/templates/default/app/api/endpoints.py
create_agent/templates/default/app/api/models.py
create_agent/templates/default/app/core/llm.py
create_agent/templates/default/app/rag/graph.py
create_agent/templates/default/app/rag/models.py
create_agent/templates/default/app/rag/nodes.py
create_agent/templates/default/app/rag/tools.py
create_agent/templates/default/app/services/chat_service.py
create_agent/templates/default/app/utils/helpers.py
create_agent/templates/default/app/utils/logging.py
create_agent/templates/default/app/utils/prompts.py
create_agent-0.0.3.dist-info/licenses/LICENSE
create_agent-0.0.3.dist-info/METADATA
create_agent-0.0.3.dist-info/WHEEL
create_agent-0.0.3.dist-info/entry_points.txt
create_agent-0.0.3.dist-info/top_level.txt
create_agent-0.0.3.dist-info/RECORD
